Metadata-Version: 2.1
Name: diffErrBnk
Version: 0.0.1
Summary: 用于自动化修复Wwise升级2022版本后，安卓平台bnk构建异常的问题
Home-page: https://github.com/SOH4C4759/diffBnk
Author: Sora
